hnt_sap_notify/RPA_HNT_Constants.py
hnt_sap_notify/__init__.py
hnt_sap_notify/hnt_sap_gui.py
hnt_sap_notify/common/hnt_sap_exception.py
hnt_sap_notify/common/session.py
hnt_sap_notify/common/tx_result.py
hnt_sap_notify/transaction/me2n_transaction.py
hnt_sap_notify/transaction/se16n_SWWUSERWI_transaction.py
hnt_sap_notify/transaction/se16n_SWWWIHEAD_transaction.py
hnt_sap_notify/transaction/su01_transaction.py
hnt_sap_notify_library-0.0.2.dist-info/METADATA
hnt_sap_notify_library-0.0.2.dist-info/WHEEL
hnt_sap_notify_library-0.0.2.dist-info/top_level.txt
hnt_sap_notify_library-0.0.2.dist-info/RECORD
