Metadata-Version: 2.1
Name: hnt-sap-notify-library
Version: 0.0.2
Summary: Lib to access sap gui to run transactions
Author: Pepe
License: MIT License
Keywords: notity
Requires-Dist: python-dotenv
Requires-Dist: robotframework-sapguilibrary
